hit_out_rem/__init__.py
hit_out_rem/outlieR.py
outlier_rem_101703235-0.0.1.dist-info/LICENSE
outlier_rem_101703235-0.0.1.dist-info/METADATA
outlier_rem_101703235-0.0.1.dist-info/WHEEL
outlier_rem_101703235-0.0.1.dist-info/entry_points.txt
outlier_rem_101703235-0.0.1.dist-info/top_level.txt
outlier_rem_101703235-0.0.1.dist-info/RECORD
