Metadata-Version: 2.1
Name: outlier-rem-101703235
Version: 0.0.1
Summary: A python package to implement outlier_removal using IQR
Home-page: https://github.com/pypa/Topsis
Author: Hitesh Gupta
Author-email: phoenixhitesh8@gmail.com
License: UNKNOWN
Platform: UNKNOWN
Classifier: Programming Language :: Python :: 3
Classifier: License :: OSI Approved :: MIT License
Classifier: Operating System :: OS Independent
Requires-Python: >=3
Requires-Dist: requests
